codeshot/__init__.py
codeshot/converter.py
codeshot/main.py
codeshot-0.2.dist-info/METADATA
codeshot-0.2.dist-info/RECORD
codeshot-0.2.dist-info/WHEEL
codeshot-0.2.dist-info/entry_points.txt
codeshot-0.2.dist-info/top_level.txt
